include/axel/BoundingBox.h
include/axel/Bvh.h
include/axel/BvhBase.h
include/axel/BvhCommon.h
include/axel/BvhEmbree.h
include/axel/BvhFactory.h
include/axel/Checks.h
include/axel/DualContouring.h
include/axel/KdTree.h
include/axel/Log.h
include/axel/MeshToSdf.h
include/axel/Profile.h
include/axel/Ray.h
include/axel/SignedDistanceField.h
include/axel/SimdKdTree.h
include/axel/TriBvh.h
include/axel/TriBvhEmbree.h
include/axel/common/Constants.h
include/axel/common/Types.h
include/axel/common/VectorizationTypes.h
include/axel/math/BoundingBoxUtils.h
include/axel/math/ContinuousCollisionDetection.h
include/axel/math/CoplanarityCheck.h
include/axel/math/EdgeEdgeDistance.h
include/axel/math/MeshHoleFilling.h
include/axel/math/PointTriangleProjection.h
include/axel/math/PointTriangleProjectionDefinitions.h
include/axel/math/RayTriangleIntersection.h
include/momentum/character/blend_shape.h
include/momentum/character/blend_shape_base.h
include/momentum/character/blend_shape_skinning.h
include/momentum/character/character.h
include/momentum/character/character_state.h
include/momentum/character/character_utility.h
include/momentum/character/collision_geometry.h
include/momentum/character/collision_geometry_state.h
include/momentum/character/fwd.h
include/momentum/character/inverse_parameter_transform.h
include/momentum/character/joint.h
include/momentum/character/joint_state.h
include/momentum/character/linear_skinning.h
include/momentum/character/locator.h
include/momentum/character/locator_state.h
include/momentum/character/marker.h
include/momentum/character/mesh_state.h
include/momentum/character/parameter_limits.h
include/momentum/character/parameter_transform.h
include/momentum/character/pose_shape.h
include/momentum/character/skeleton.h
include/momentum/character/skeleton_state.h
include/momentum/character/skeleton_utility.h
include/momentum/character/skin_weights.h
include/momentum/character/skinned_locator.h
include/momentum/character/types.h
pymomentum_cpu-0.1.103.post0.dist-info/METADATA
pymomentum_cpu-0.1.103.post0.dist-info/WHEEL
pymomentum_cpu-0.1.103.post0.dist-info/licenses/LICENSE
pymomentum_cpu-0.1.103.post0.dist-info/RECORD
