Metadata-Version: 2.1
Name: pymomentum-cpu
Version: 0.1.103.post0
Summary: A library providing foundational algorithms for human kinematic motion and numerical optimization solvers to apply human motion in various applications (CPU-only version for Linux, macOS Intel, and macOS ARM)
Keywords: kinematics,motion,optimization,human-motion,inverse-kinematics,forward-kinematics,body-tracking,motion-capture,character-animation,robotics,cpu
Author-Email: Meta Reality Labs Research <jeongseok@meta.com>
License: MIT
Classifier: Development Status :: 4 - Beta
Classifier: Intended Audience :: Developers
Classifier: Intended Audience :: Science/Research
Classifier: License :: OSI Approved :: MIT License
Classifier: Operating System :: POSIX :: Linux
Classifier: Operating System :: MacOS
Classifier: Programming Language :: C++
Classifier: Programming Language :: Python :: 3
Classifier: Programming Language :: Python :: 3.12
Classifier: Programming Language :: Python :: 3.13
Classifier: Programming Language :: Python :: Implementation :: CPython
Classifier: Topic :: Scientific/Engineering
Classifier: Topic :: Scientific/Engineering :: Mathematics
Classifier: Topic :: Scientific/Engineering :: Physics
Classifier: Topic :: Software Development :: Libraries :: Python Modules
Project-URL: Homepage, https://github.com/facebookresearch/momentum
Project-URL: Documentation, https://facebookresearch.github.io/momentum/
Project-URL: Repository, https://github.com/facebookresearch/momentum
Project-URL: Bug tracker, https://github.com/facebookresearch/momentum/issues
Project-URL: Changelog, https://github.com/facebookresearch/momentum/releases
Requires-Python: <3.13,>=3.12
Requires-Dist: numpy>=1.20.0
Requires-Dist: scipy>=1.7.0
Requires-Dist: torch<2.9,>=2.8.0; platform_system == "Linux" and python_version == "3.12"
Requires-Dist: torch<2.9,>=2.8.0; platform_system == "Linux" and python_version == "3.13"
Requires-Dist: torch<2.9,>=2.8.0; platform_system == "Darwin" and platform_machine == "arm64" and python_version == "3.12"
Requires-Dist: torch<2.9,>=2.8.0; platform_system == "Darwin" and platform_machine == "arm64" and python_version == "3.13"
